sdk/bulk_update_request.py
sdk/bulk_update_response.py
sdk/client.py
sdk/comment.py
sdk/comment_author.py
sdk/comment_collection.py
sdk/comment_reaction.py
sdk/comments_tag.py
sdk/delete_response.py
sdk/error.py
sdk/error_details.py
sdk/error_exception.py
sdk/field.py
sdk/field_options.py
sdk/fields_tag.py
sdk/meta_tag.py
sdk/record.py
sdk/record_collection.py
sdk/records_tag.py
sdk/table.py
sdk/tables_tag.py
sdk/user.py
sdkfabric_airtable-0.4.2.dist-info/LICENSE
sdkfabric_airtable-0.4.2.dist-info/METADATA
sdkfabric_airtable-0.4.2.dist-info/WHEEL
sdkfabric_airtable-0.4.2.dist-info/top_level.txt
sdkfabric_airtable-0.4.2.dist-info/RECORD
